Metadata-Version: 2.1
Name: rqdatac-news
Version: 0.1.1
Summary: rqdatac news extension
Home-page: https://www.ricequant.com/
Author: Ricequant
Author-email: public@ricequant.com
Keywords: rqdatac_news
Classifier: Programming Language :: Python
Classifier: Programming Language :: Python :: 2
Classifier: Programming Language :: Python :: 2.7
Classifier: Programming Language :: Python :: 3
Classifier: Programming Language :: Python :: 3.4
Classifier: Programming Language :: Python :: 3.5
Classifier: Programming Language :: Python :: 3.6
Classifier: Programming Language :: Python :: 3.7
Classifier: Programming Language :: Python :: 3.8
Classifier: Intended Audience :: Developers
Classifier: Operating System :: OS Independent
Classifier: Environment :: Console
Requires-Python: >=2.7, <4
